src/adder.sv
`timescale 1ns/1ps
module adder (
    input  logic                clk,
    input  logic                rst_n,
    input  logic signed [15:0]  in1,
    input  logic signed [7:0]   in2,
    output logic signed [15:0]  sum,
    output logic                carry
);

    wire signed [15:0] sign_ext = {{8{in2[7]}}, in2};
    logic signed [16:0] temp;

    always @(posedge clk or negedge rst_n) begin
        if (!rst_n)
            temp <= 17'sd0;
        else
            temp <= in1 + sign_ext;
    end
   
    assign sum   = temp[15:0];
    assign carry = temp[16];

endmodule

functional/adder_tb.sv
`timescale 1ns/1ps

module adder_tb;

    // Testbench signals
    logic clk;
    logic rst_n;
    logic signed [15:0] in1;
    logic signed [7:0]  in2;
    logic signed [15:0] sum;
    logic carry;

    // Expected output
    logic signed [15:0] expected_sum;
    logic expected_carry;

    // Counters
    integer total_tests = 0;
    integer passed_tests = 0;

    // Instantiate DUT
    adder dut (
        .clk(clk),
        .rst_n(rst_n),
        .in1(in1),
        .in2(in2),
        .sum(sum),
        .carry(carry)
    );

    // Clock generation
    always #5 clk = ~clk;

    // Apply inputs and check results after clock
    task automatic run_test(
        input logic signed [15:0] a,
        input logic signed [7:0]  b
    );
        logic signed [16:0] temp;
        begin
            in1 = a;
            in2 = b;
            temp = a + $signed({{8{b[7]}}, b}); // manual sign extension
            expected_sum = temp[15:0];
            expected_carry = temp[16];

            @(posedge clk); #1; // Wait for result update

            total_tests++;
            if (sum === expected_sum && carry === expected_carry) begin
                $display("Passed: %0d + %0d = %0d, carry = %0b", a, b, sum, carry);
                passed_tests++;
            end else begin
                $display(" Failed: %0d + %0d", a, b);
                $display("   Expected sum = %0d, carry = %0b", expected_sum, expected_carry);
                $display("   Got      sum = %0d, carry = %0b", sum, carry);
            end
        end
    endtask

    initial begin
        $dumpfile("adder.vcd");
        $dumpvars(0, adder_tb);

        // Init
        clk = 0;
        rst_n = 0;
        in1 = 0;
        in2 = 0;

        #10;
        rst_n = 1;

        // Basic tests
        run_test(16'sd100, 8'sd27);       // 100 + 27 = 127
        run_test(16'sd50, -8'sd20);       // 50 + (-20) = 30
        run_test(-16'sd120, 8'sd50);      // -120 + 50 = -70
        run_test(-16'sd128, -8'sd1);      // -128 -1 = -129
        run_test(16'sd32767, 8'sd1);      // overflow case: 32767 + 1

        // Randomized tests
        repeat (10) begin
            run_test($random, $random);
        end

        $display("Testbench finished: %0d/%0d passed", passed_tests, total_tests);
        $finish;
    end

endmodule

adder.vcd
$date
	Wed Jul 23 19:45:54 2025
$end
$version
	Icarus Verilog
$end
$timescale
	1ps
$end
$scope module adder_tb $end
$var wire 16 ! sum [15:0] $end
$var wire 1 " carry $end
$var reg 1 # clk $end
$var reg 1 $ expected_carry $end
$var reg 16 % expected_sum [15:0] $end
$var reg 16 & in1 [15:0] $end
$var reg 8 ' in2 [7:0] $end
$var reg 1 ( rst_n $end
$var integer 32 ) passed_tests [31:0] $end
$var integer 32 * total_tests [31:0] $end
$scope module dut $end
$var wire 1 # clk $end
$var wire 16 + in1 [15:0] $end
$var wire 8 , in2 [7:0] $end
$var wire 1 ( rst_n $end
$var wire 16 - sum [15:0] $end
$var wire 16 . sign_ext [15:0] $end
$var wire 1 " carry $end
$var reg 17 / temp [16:0] $end
$upscope $end
$scope task run_test $end
$upscope $end
$upscope $end
$enddefinitions $end
#0
$dumpvars
b0 /
b0 .
b0 -
b0 ,
b0 +
b0 *
b0 )
0(
b0 '
b0 &
bx %
x$
0#
0"
b0 !
$end
#5000
1#
#10000
0#
0$
b1111111 %
b11011 .
b11011 '
b11011 ,
b1100100 &
b1100100 +
1(
#15000
b1111111 !
b1111111 -
b1111111 /
1#
#16000
b11110 %
b1111111111101100 .
b11101100 '
b11101100 ,
b110010 &
b110010 +
b1 )
b1 *
#20000
0#
#25000
b11110 !
b11110 -
b11110 /
1#
#26000
1$
b1111111110111010 %
b110010 .
b110010 '
b110010 ,
b1111111110001000 &
b1111111110001000 +
b10 )
b10 *
#30000
0#
#35000
b1111111110111010 !
b1111111110111010 -
1"
b11111111110111010 /
1#
#36000
b1111111101111111 %
b1111111111111111 .
b11111111 '
b11111111 ,
b1111111110000000 &
b1111111110000000 +
b11 )
b11 *
#40000
0#
#45000
b1111111101111111 !
b1111111101111111 -
b11111111101111111 /
1#
#46000
0$
b1000000000000000 %
b1 .
b1 '
b1 ,
b111111111111111 &
b111111111111111 +
b100 )
b100 *
#50000
0#
#55000
b1000000000000000 !
b1000000000000000 -
0"
b1000000000000000 /
1#
#56000
b11010010100101 %
b1111111110000001 .
b10000001 '
b10000001 ,
b11010100100100 &
b11010100100100 +
b101 )
b101 *
#60000
0#
#65000
b11010010100101 !
b11010010100101 -
b11010010100101 /
1#
#66000
1$
b1101011001101100 %
b1100011 .
b1100011 '
b1100011 ,
b1101011000001001 &
b1101011000001001 +
b110 )
b110 *
#70000
0#
#75000
b1101011001101100 !
b1101011001101100 -
1"
b11101011001101100 /
1#
#76000
0$
b111101010011010 %
b1111111110001101 .
b10001101 '
b10001101 ,
b111101100001101 &
b111101100001101 +
b111 )
b111 *
#80000
0#
#85000
b111101010011010 !
b111101010011010 -
0"
b111101010011010 /
1#
#86000
1$
b1000010001110111 %
b10010 .
b10010 '
b10010 ,
b1000010001100101 &
b1000010001100101 +
b1000 )
b1000 *
#90000
0#
#95000
b1000010001110111 !
b1000010001110111 -
1"
b11000010001110111 /
1#
#96000
b1110001100001110 %
b1101 .
b1101 '
b1101 ,
b1110001100000001 &
b1110001100000001 +
b1001 )
b1001 *
#100000
0#
#105000
b1110001100001110 !
b1110001100001110 -
b11110001100001110 /
1#
#106000
b1111000110110011 %
b111101 .
b111101 '
b111101 ,
b1111000101110110 &
b1111000101110110 +
b1010 )
b1010 *
#110000
0#
#115000
b1111000110110011 !
b1111000110110011 -
b11111000110110011 /
1#
#116000
0$
b101011101111001 %
b1111111110001100 .
b10001100 '
b10001100 ,
b101011111101101 &
b101011111101101 +
b1011 )
b1011 *
#120000
0#
#125000
b101011101111001 !
b101011101111001 -
0"
b101011101111001 /
1#
#126000
1$
b1110100110111111 %
b1111111111000110 .
b11000110 '
b11000110 ,
b1110100111111001 &
b1110100111111001 +
b1100 )
b1100 *
#130000
0#
#135000
b1110100110111111 !
b1110100110111111 -
1"
b11110100110111111 /
1#
#136000
b1000010001101111 %
b1111111110101010 .
b10101010 '
b10101010 ,
b1000010011000101 &
b1000010011000101 +
b1101 )
b1101 *
#140000
0#
#145000
b1000010001101111 !
b1000010001101111 -
b11000010001101111 /
1#
#146000
b1111100001011100 %
b1110111 .
b1110111 '
b1110111 ,
b1111011111100101 &
b1111011111100101 +
b1110 )
b1110 *
#150000
0#
#155000
b1111100001011100 !
b1111100001011100 -
b11111100001011100 /
1#
#156000
b1111 )
b1111 *
